llama_index/packs/ragatouille_retriever/__init__.py
llama_index/packs/ragatouille_retriever/base.py
llama_index_packs_ragatouille_retriever-0.5.1.dist-info/METADATA
llama_index_packs_ragatouille_retriever-0.5.1.dist-info/WHEEL
llama_index_packs_ragatouille_retriever-0.5.1.dist-info/licenses/LICENSE
llama_index_packs_ragatouille_retriever-0.5.1.dist-info/RECORD
