Metadata-Version: 2.4
Name: llama-index-packs-ragatouille-retriever
Version: 0.5.1
Summary: llama-index packs ragatouille_retriever integration
Author-email: Your Name <you@example.com>
Maintainer: jerryjliu
License-Expression: MIT
License-File: LICENSE
Keywords: rag,ragatouille,retriever
Requires-Python: <4.0,>=3.9
Requires-Dist: llama-index-core<0.15,>=0.13.0
Requires-Dist: llama-index-llms-openai<0.6,>=0.5.0
